Metadata-Version: 1.0
Name: k-probability
Version: 1.0
Summary: Gaussian distributions
Home-page: UNKNOWN
Author: Khalid Alolayan
Author-email: UNKNOWN
License: UNKNOWN
Platform: UNKNOWN
